alibabacloud_imp20210630/__init__.py
alibabacloud_imp20210630/client.py
alibabacloud_imp20210630/models.py
alibabacloud_imp20210630-2.9.9.dist-info/LICENSE
alibabacloud_imp20210630-2.9.9.dist-info/METADATA
alibabacloud_imp20210630-2.9.9.dist-info/WHEEL
alibabacloud_imp20210630-2.9.9.dist-info/top_level.txt
alibabacloud_imp20210630-2.9.9.dist-info/RECORD
